setup.py
Flask_WebCache.egg-info/PKG-INFO
Flask_WebCache.egg-info/SOURCES.txt
Flask_WebCache.egg-info/dependency_links.txt
Flask_WebCache.egg-info/not-zip-safe
Flask_WebCache.egg-info/requires.txt
Flask_WebCache.egg-info/top_level.txt
flask_webcache/__init__.py
flask_webcache/handlers.py
flask_webcache/modifiers.py
flask_webcache/recache.py
flask_webcache/storage.py
flask_webcache/utils.py
flask_webcache/validation.py