Metadata-Version: 1.0
Name: Flask-WebCache
Version: 0.7
Summary: A Flask extension that adds HTTP based caching to Flask apps
Home-page: http://github.com/fusic-com/flask-webcache/
Author: Yaniv Aknin
Author-email: yaniv@aknin.name
License: BSD
Platform: any
Classifier: Environment :: Web Environment
Classifier: Intended Audience :: Developers
Classifier: License :: OSI Approved :: BSD License
Classifier: Operating System :: OS Independent
Classifier: Programming Language :: Python :: 2.7
Classifier: Topic :: Internet :: WWW/HTTP :: Dynamic Content
Classifier: Topic :: Software Development :: Libraries :: Python Modules
Classifier: Development Status :: 3 - Alpha
